{"Id":"311100a8-fb6d-4636-9d9b-8d0cb3c6672b","LogDateUtc":"2020-08-02T12:54:30.221589Z","IpAddress":"::1","Culture":"en-GB","Url":"/lara","ShortUrl":"/lara","Thread":"","LogLevel":"Information","Logger":"Microsoft.AspNetCore.Mvc.ViewFeatures.ViewResultExecutor","Message":"Executed ViewResult - view Index executed in 22.221400000000003ms.","StateJson":"[{\"Key\":\"ViewName\",\"Value\":\"Index\"},{\"Key\":\"ElapsedMilliseconds\",\"Value\":22.221400000000003},{\"Key\":\"{OriginalFormat}\",\"Value\":\"Executed ViewResult - view {ViewName} executed in {ElapsedMilliseconds}ms.\"}]","EventId":4}