{"Id":"45bee441-53a8-4d01-8d4c-b9014a1856fb","LogDateUtc":"2020-08-02T12:57:52.635557Z","IpAddress":"::1","Culture":"en-GB","Url":"/lara","ShortUrl":"/lara","Thread":"","LogLevel":"Information","Logger":"Microsoft.AspNetCore.Mvc.Infrastructure.ControllerActionInvoker","Message":"Executed action cloudscribe.SimpleContent.Web.Mvc.Controllers.PageController.Index (cloudscribe.SimpleContent.Web) in 10.5637ms","StateJson":"[{\"Key\":\"ActionName\",\"Value\":\"cloudscribe.SimpleContent.Web.Mvc.Controllers.PageController.Index (cloudscribe.SimpleContent.Web)\"},{\"Key\":\"ElapsedMilliseconds\",\"Value\":10.5637},{\"Key\":\"{OriginalFormat}\",\"Value\":\"Executed action {ActionName} in {ElapsedMilliseconds}ms\"}]","EventId":2}