{"Id":"54e59116-dfb7-475b-9780-0f1cc55455c6","LogDateUtc":"2020-08-02T12:47:05.147879Z","IpAddress":"::1","Culture":"en-GB","Url":"/clients","ShortUrl":"/clients","Thread":"","LogLevel":"Information","Logger":"Microsoft.AspNetCore.Mvc.Infrastructure.ControllerActionInvoker","Message":"Executed action cloudscribe.Core.IdentityServerIntegration.Controllers.Mvc.ClientsController.Index (cloudscribe.Core.IdentityServerIntegration) in 61.2091ms","StateJson":"[{\"Key\":\"ActionName\",\"Value\":\"cloudscribe.Core.IdentityServerIntegration.Controllers.Mvc.ClientsController.Index (cloudscribe.Core.IdentityServerIntegration)\"},{\"Key\":\"ElapsedMilliseconds\",\"Value\":61.2091},{\"Key\":\"{OriginalFormat}\",\"Value\":\"Executed action {ActionName} in {ElapsedMilliseconds}ms\"}]","EventId":2}