{"Id":"5547323a-9bdc-4660-9dac-e350af838470","LogDateUtc":"2020-08-02T12:56:12.779135Z","IpAddress":"::1","Culture":"en-GB","Url":"/editwithtemplate/lara","ShortUrl":"/editwithtemplate/lara","Thread":"","LogLevel":"Information","Logger":"Microsoft.AspNetCore.Mvc.RedirectToRouteResult","Message":"Executing RedirectToRouteResult, redirecting to /lara from route pageindex.","StateJson":"[{\"Key\":\"Destination\",\"Value\":\"/lara\"},{\"Key\":\"RouteName\",\"Value\":\"pageindex\"},{\"Key\":\"{OriginalFormat}\",\"Value\":\"Executing RedirectToRouteResult, redirecting to {Destination} from route {RouteName}.\"}]","EventId":1}