{"Id":"b11c2698-e8ec-48d1-ab79-e92b0274c1c1","LogDateUtc":"2020-08-02T12:53:14.139536Z","IpAddress":"::1","Culture":"en-GB","Url":"/page/tree","ShortUrl":"/page/tree","Thread":"","LogLevel":"Information","Logger":"Microsoft.AspNetCore.Mvc.ViewFeatures.ViewResultExecutor","Message":"Executed ViewResult - view Tree executed in 24.4923ms.","StateJson":"[{\"Key\":\"ViewName\",\"Value\":\"Tree\"},{\"Key\":\"ElapsedMilliseconds\",\"Value\":24.4923},{\"Key\":\"{OriginalFormat}\",\"Value\":\"Executed ViewResult - view {ViewName} executed in {ElapsedMilliseconds}ms.\"}]","EventId":4}