{"Id":"689e909b-53ba-47f1-ade0-4d2fe2d115b9","LogDateUtc":"2020-08-02T12:57:50.46209Z","IpAddress":"::1","Culture":"en-GB","Url":"/sctr/css/simple-gallery.min.css","ShortUrl":"/sctr/css/simple-gallery.min.css","Thread":"","LogLevel":"Debug","Logger":"cloudscribe.SimpleContent.ContentTemplates.Bootstrap4.Controllers.SctrController","Message":"/sctr/css/simple-gallery.min.css requested","StateJson":"[{\"Key\":\"{OriginalFormat}\",\"Value\":\"/sctr/css/simple-gallery.min.css requested\"}]","EventId":0}