{"Id":"809a5a37-fe49-4b9e-b53b-540f7c124825","LogDateUtc":"2020-08-02T12:51:21.842841Z","IpAddress":"::1","Culture":"en-GB","Url":"/page/inittemplatedpage","ShortUrl":"/page/inittemplatedpage","Thread":"","LogLevel":"Debug","Logger":"cloudscribe.Web.Localization.CultureSegmentRouteConstraint","Message":"did not match culture route constraint for path /page/inittemplatedpage","StateJson":"[{\"Key\":\"{OriginalFormat}\",\"Value\":\"did not match culture route constraint for path /page/inittemplatedpage\"}]","EventId":0}